{
  "$schema": "https://schema.management.azure.com/schemas/2015-01-01/deploymentParameters.json#",
  "contentVersion": "1.0.0.0",
  "parameters": {
    "spokeVnetName": {
      "value": "vnet-spoke-w0102"
    },
    "nsgName": {
      "value": "nsg-workload-w0102"
    },
    "spokeVnetPrefix": {
      "value": "10.102.0.0/16"
    },
    "spokeResourceSubnetPrefix": {
      "value": "10.102.1.0/24"
    },
    "spokeBastionSubnetPrefix": {
      "value": "10.102.251.0/24"
    },
    "deployBastion": {
      "value": false
    }
  }
}